tangogateway/__init__.py
tangogateway/__main__.py
tangogateway/_version.py
tangogateway/cli.py
tangogateway/gateway.py
tangogateway/giop.py
tangogateway/zmqforward.py
tango_gateway-1.2.0.dist-info/LICENSE.txt
tango_gateway-1.2.0.dist-info/METADATA
tango_gateway-1.2.0.dist-info/WHEEL
tango_gateway-1.2.0.dist-info/entry_points.txt
tango_gateway-1.2.0.dist-info/top_level.txt
tango_gateway-1.2.0.dist-info/RECORD
