Metadata-Version: 2.1
Name: tango-gateway
Version: 1.2.0
Summary: A Tango gateway server
Author-email: Vincent Michel <vincent.michel@maxlab.lu.se>, KITS Software <kits-sw@maxiv.lu.se>
License: GNU GENERAL PUBLIC LICENSE
Project-URL: Homepage, http://www.maxiv.lu.se
Project-URL: Repository, https://gitlab.com/MaxIV/tango-gateway
Keywords: Tango
Requires-Python: >=3.9
License-File: LICENSE.txt
Requires-Dist: aiozmq
